{
"scale_to_square_image_in_notifications":false,
"sponsor_block_enable":true,
"resume_on_audio_focus_gain":true,
"tablet_mode":"off",
"screen_brightness_timestamp_key":1767732079198,
"is_in_background":true,
"popup_remember_size_pos_key":true,
"show_original_time_ago_key":false,
"limit_mobile_data_usage":"360p",
"enable_playback_state_lists":true,
"sponsor_block_category_interaction_mode":"Automatic",
"channel_tabs":["show_channel_tabs_livestreams","show_channel_tabs_videos","show_channel_tabs_albums","show_channel_tabs_channels","show_channel_tabs_tracks","show_channel_tabs_about","show_channel_tabs_shorts","show_channel_tabs_playlists"],
"streams_notifications_interval":"14400",
"use_exoplayer_decoder_fallback_key":false,
"popup_saved_width":732.0,
"default_popup_resolution":"240p",
"show_higher_resolutions":false,
"sponsor_block_category_music_color":"#ffff9900",
"return_youtube_dislike_enable":true,
"last_resize_mode":0,
"use_external_video_player":false,
"show_comments":true,
"sponsor_block_notifications":true,
"show_thumbnail_key":true,
"feed_show_played_items":true,
"sponsor_block_graced_rewind":true,
"sponsor_block_category_promo_mode":"Automatic",
"return_youtube_dislike_api_url":"https://returnyoutubedislikeapi.com/",
"show_crash_the_player_key":false,
"download_path_audio":"content://com.android.providers.downloads.documents/tree/downloads",
"prefer_original_audio":true,
"popup_saved_x":279,
"feed_update_threshold_key":"300",
"popup_saved_y":1801,
"notification_colorize_key":true,
"sponsor_block_category_intro_color":"#ff00ffff",
"sponsor_block_category_outro_mode":"Automatic",
"streams_notifications_network":"wifi",
"enable_streams_notifications":false,
"right_gesture_control":"none_control",
"autoplay_key":"autoplay_always_key",
"sponsor_block_category_music":true,
"prefer_descriptive_audio":false,
"media_tunneling_device_blacklist_version":994,
"feed_show_future_items":false,
"content_language":"system",
"image_quality_key":"image_quality_medium",
"sponsor_block_category_music_mode":"Automatic",
"enable_search_history":true,
"default_download_threads":6,
"show_meta_info":true,
"key_theme_change":false,
"preferred_open_action_key":"popup_player",
"theme":"dark_theme",
"sponsor_block_category_sponsor":true,
"caption_user_set_key":"français (auto-generated)",
"default_video_format":"video_mp4",
"linear":false,
"show_description":true,
"sponsor_block_category_preview_color":"#ff008fd6",
"last_used_preferences_version":8,
"sponsor_block_category_outro":true,
"seekbar_preview_thumbnail_key":"seekbar_preview_thumbnail_high_quality",
"sponsor_block_category_filler":true,
"left_gesture_control":"none_control",
"return_youtube_dislike_show_dislikes_as_percentage":true,
"sponsor_block_category_intro":true,
"middle_gesture_control":"none_control",
"sponsor_block_category_outro_color":"#ff0202ed",
"sponsor_block_api_url":"https://sponsor.ajay.app/api/",
"show_hold_to_append":false,
"downloads_queue_limit":true,
"sponsor_block_category_highlight":true,
"use_inexact_seek_key":true,
"show_age_restricted_content":true,
"always_use_exoplayer_set_output_surface_workaround_key":false,
"clear_queue_confirmation_key":false,
"last_dl_type_video":"last_dl_type_audio",
"auto_queue_key":false,
"night_theme":"dark_theme",
"playback_skip_silence_key":false,
"enable_playback_resume":true,
"file_replacement_character":"_",
"update_app_key":false,
"default_resolution":"360p",
"downloads_max_retry":"3",
"content_country":"US",
"show_next_video":true,
"downloads_storage_ask":false,
"download_path":"content://com.android.externalstorage.documents/tree/primary%3ADownload%2FOsef",
"sponsor_block_category_interaction_color":"#ffcc00ff",
"max_playback_speed":"3",
"list_view_mode":"auto",
"sponsor_block_category_filler_mode":"Automatic",
"cross_network_downloads":false,
"sponsor_block_category_interaction":true,
"return_youtube_dislike_override_view_count":true,
"allow_heap_dumping_key":false,
"return_youtube_dislike_override_like_count":true,
"feed_fetch_channel_tabs":["fetch_channel_tabs_videos","fetch_channel_tabs_livestreams","fetch_channel_tabs_likes"],
"sponsor_block_category_pending_color_key":"#ffffffff",
"saved_tabs_key":"{\"tabs\":[{\"tab_id\":1},{\"tab_id\":4},{\"tab_id\":3}]}",
"storage_use_saf":true,
"feed_use_dedicated_fetch_method":false,
"show_image_indicators_key":false,
"sponsor_block_category_sponsor_mode":"Automatic",
"show_search_suggestions":["show_local_search_suggestions","show_remote_search_suggestions"],
"progressive_load_interval":"64",
"sponsor_block_category_highlight_color":"#ffff1983",
"start_main_player_fullscreen_key":false,
"youtube_restricted_mode_enabled":false,
"playback_pitch_key":1.0,
"show_kiosks":true,
"file_rename_charset":"CHARSET_MOST_SPECIAL",
"sponsor_block_category_preview":true,
"enable_watch_history":true,
"ignore_hardware_media_buttons_key":false,
"middle_gesture_area_width":".25",
"main_tabs_position":false,
"sponsor_block_category_self_promo_color":"#ffffff00",
"sponsor_block_show_manual_skip":true,
"sponsor_block_category_filler_color":"#ff7300ff",
"disable_media_tunneling_key":false,
"minimize_on_exit_key":"minimize_on_exit_popup_key",
"allow_disposed_exceptions_key":false,
"seek_on_media_button_events_key":false,
"preferred_open_action_last_selected":"popup_player",
"use_external_audio_player":false,
"import_export_data_path":"content://com.android.providers.downloads.documents/document/4042",
"feed_show_partially_watched_items":true,
"sponsor_block_category_intro_mode":"Automatic",
"kao_last_checked":1778494298478,
"sponsor_block_category_self_promo":true,
"default_audio_format":"audio_m4a",
"playback_speed_key":1.0,
"show_play_with_kodi":false,
"seek_duration":"10000",
"service":"YouTube",
"stream_info_selected_tab":"COMMENTS",
"sponsor_block_category_preview_mode":"Automatic",
"sponsor_block_category_sponsor_color":"#ff00d400"
}